[
  { "id": "team-001", "text": "Best Lakers of All Time", "type": "team", "leagues": ["NBA"] },
  { "id": "team-002", "text": "Greatest Cowboys Ever", "type": "team", "leagues": ["NFL"] },
  { "id": "team-003", "text": "All-Time Steelers Defense", "type": "team", "leagues": ["NFL"] },
  { "id": "team-004", "text": "Best Yankees of All Time", "type": "team", "leagues": ["MLB"] },
  { "id": "team-005", "text": "Greatest Celtics Ever", "type": "team", "leagues": ["NBA"] },
  { "id": "team-006", "text": "All-Time Bulls Roster", "type": "team", "leagues": ["NBA"] },
  { "id": "team-007", "text": "Best Patriots Ever", "type": "team", "leagues": ["NFL"] },
  { "id": "team-008", "text": "Greatest Warriors of All Time", "type": "team", "leagues": ["NBA"] },
  { "id": "team-009", "text": "All-Time 49ers Offense", "type": "team", "leagues": ["NFL"] },
  { "id": "team-010", "text": "Best Red Sox Players Ever", "type": "team", "leagues": ["MLB"] },
  { "id": "team-011", "text": "Greatest Heat Players of All Time", "type": "team", "leagues": ["NBA"] },
  { "id": "team-012", "text": "All-Time Raiders Roster", "type": "team", "leagues": ["NFL"] },
  { "id": "team-013", "text": "Best Dodgers of All Time", "type": "team", "leagues": ["MLB"] },
  { "id": "team-014", "text": "Greatest Packers Ever", "type": "team", "leagues": ["NFL"] },
  { "id": "team-015", "text": "All-Time Spurs Roster", "type": "team", "leagues": ["NBA"] },
  { "id": "team-016", "text": "Best Cardinals (MLB) of All Time", "type": "team", "leagues": ["MLB"] },
  { "id": "team-017", "text": "Greatest Eagles Players Ever", "type": "team", "leagues": ["NFL"] },
  { "id": "team-018", "text": "All-Time Canadiens Roster", "type": "team", "leagues": ["NHL"] },
  { "id": "team-019", "text": "Best Knicks of All Time", "type": "team", "leagues": ["NBA"] },
  { "id": "team-020", "text": "Greatest Ravens Defense Ever", "type": "team", "leagues": ["NFL"] },
  { "id": "team-021", "text": "All-Time Red Wings Roster", "type": "team", "leagues": ["NHL"] },
  { "id": "team-022", "text": "Best Rockets of All Time", "type": "team", "leagues": ["NBA"] },
  { "id": "team-023", "text": "Greatest Cubs Players Ever", "type": "team", "leagues": ["MLB"] },
  { "id": "team-024", "text": "All-Time Seahawks Roster", "type": "team", "leagues": ["NFL"] },
  { "id": "team-025", "text": "Best 76ers of All Time", "type": "team", "leagues": ["NBA"] },

  { "id": "position-001", "text": "Best Point Guards Ever", "type": "position", "leagues": ["NBA"] },
  { "id": "position-002", "text": "Most Dominant Pitchers of All Time", "type": "position", "leagues": ["MLB"] },
  { "id": "position-003", "text": "Greatest Shutdown Cornerbacks", "type": "position", "leagues": ["NFL"] },
  { "id": "position-004", "text": "Best Centers in NBA History", "type": "position", "leagues": ["NBA"] },
  { "id": "position-005", "text": "Greatest Quarterbacks of All Time", "type": "position", "leagues": ["NFL"] },
  { "id": "position-006", "text": "Best Shooting Guards Ever", "type": "position", "leagues": ["NBA"] },
  { "id": "position-007", "text": "Most Dominant Running Backs", "type": "position", "leagues": ["NFL"] },
  { "id": "position-008", "text": "Greatest Goalies in NHL History", "type": "position", "leagues": ["NHL"] },
  { "id": "position-009", "text": "Best Power Forwards of All Time", "type": "position", "leagues": ["NBA"] },
  { "id": "position-010", "text": "Greatest Wide Receivers Ever", "type": "position", "leagues": ["NFL"] },
  { "id": "position-011", "text": "Best Shortstops in MLB History", "type": "position", "leagues": ["MLB"] },
  { "id": "position-012", "text": "Most Dominant Defensive Ends", "type": "position", "leagues": ["NFL"] },
  { "id": "position-013", "text": "Best Small Forwards of All Time", "type": "position", "leagues": ["NBA"] },
  { "id": "position-014", "text": "Greatest Closers in MLB History", "type": "position", "leagues": ["MLB"] },
  { "id": "position-015", "text": "Best Tight Ends Ever", "type": "position", "leagues": ["NFL"] },
  { "id": "position-016", "text": "Most Dominant Middle Linebackers", "type": "position", "leagues": ["NFL"] },
  { "id": "position-017", "text": "Greatest Catchers of All Time", "type": "position", "leagues": ["MLB"] },
  { "id": "position-018", "text": "Best Offensive Linemen Ever", "type": "position", "leagues": ["NFL"] },
  { "id": "position-019", "text": "Greatest Defensemen in NHL History", "type": "position", "leagues": ["NHL"] },
  { "id": "position-020", "text": "Best Safeties of All Time", "type": "position", "leagues": ["NFL"] },

  { "id": "era-001", "text": "Best Players of the 2010s", "type": "era", "leagues": ["NBA", "NFL", "MLB", "NHL"] },
  { "id": "era-002", "text": "Greatest Rookies of All Time", "type": "era", "leagues": ["NBA", "NFL", "MLB", "NHL"] },
  { "id": "era-003", "text": "Best Players of the 1990s", "type": "era", "leagues": ["NBA", "NFL", "MLB", "NHL"] },
  { "id": "era-004", "text": "Greatest Draft Picks in History", "type": "era", "leagues": ["NBA", "NFL", "MLB", "NHL"] },
  { "id": "era-005", "text": "Best Players of the 2000s", "type": "era", "leagues": ["NBA", "NFL", "MLB", "NHL"] },
  { "id": "era-006", "text": "Most Dominant Dynasties Ever", "type": "era", "leagues": ["NBA", "NFL", "MLB", "NHL"] },
  { "id": "era-007", "text": "Greatest Players Before 1980", "type": "era", "leagues": ["NBA", "NFL", "MLB", "NHL"] },
  { "id": "era-008", "text": "Best Undrafted Players Ever", "type": "era", "leagues": ["NBA", "NFL", "MLB"] },
  { "id": "era-009", "text": "Greatest Sophomore Seasons of All Time", "type": "era", "leagues": ["NBA", "NFL", "MLB", "NHL"] },
  { "id": "era-010", "text": "Best Players of the 2020s So Far", "type": "era", "leagues": ["NBA", "NFL", "MLB", "NHL"] },
  { "id": "era-011", "text": "Greatest Late-Career Resurgences", "type": "era", "leagues": ["NBA", "NFL", "MLB", "NHL"] },
  { "id": "era-012", "text": "Best Playoff Performers in History", "type": "era", "leagues": ["NBA", "NFL", "MLB", "NHL"] },
  { "id": "era-013", "text": "Greatest Single-Season Performances", "type": "era", "leagues": ["NBA", "NFL", "MLB", "NHL"] },
  { "id": "era-014", "text": "Best Players Who Switched Teams and Got Better", "type": "era", "leagues": ["NBA", "NFL", "MLB", "NHL"] },
  { "id": "era-015", "text": "Most Iconic Championship Runs", "type": "era", "leagues": ["NBA", "NFL", "MLB", "NHL"] },

  { "id": "creative-001", "text": "Athletes You'd Want on Your Pickup Basketball Team", "type": "creative", "leagues": ["NBA", "NFL", "MLB", "NHL"] },
  { "id": "creative-002", "text": "Athletes You'd Want in a Zombie Apocalypse", "type": "creative", "leagues": ["NBA", "NFL", "MLB", "NHL"] },
  { "id": "creative-003", "text": "Players Who Changed Their Sport Forever", "type": "creative", "leagues": ["NBA", "NFL", "MLB", "NHL"] },
  { "id": "creative-004", "text": "Most Entertaining Players to Watch", "type": "creative", "leagues": ["NBA", "NFL", "MLB", "NHL"] },
  { "id": "creative-005", "text": "Athletes You'd Want as Your Neighbor", "type": "creative", "leagues": ["NBA", "NFL", "MLB", "NHL"] },
  { "id": "creative-006", "text": "Players With the Best Trash Talk", "type": "creative", "leagues": ["NBA", "NFL", "MLB", "NHL"] },
  { "id": "creative-007", "text": "Athletes Who Would Dominate Another Sport", "type": "creative", "leagues": ["NBA", "NFL", "MLB", "NHL"] },
  { "id": "creative-008", "text": "Best Nicknames in Sports History", "type": "creative", "leagues": ["NBA", "NFL", "MLB", "NHL"] },
  { "id": "creative-009", "text": "Players You'd Want to Start a Business With", "type": "creative", "leagues": ["NBA", "NFL", "MLB", "NHL"] },
  { "id": "creative-010", "text": "Most Underrated Players Your Friends Don't Know About", "type": "creative", "leagues": ["NBA", "NFL", "MLB", "NHL"] },
  { "id": "creative-011", "text": "Athletes Who'd Survive on a Deserted Island", "type": "creative", "leagues": ["NBA", "NFL", "MLB", "NHL"] },
  { "id": "creative-012", "text": "Players With the Coldest Celebrations", "type": "creative", "leagues": ["NBA", "NFL", "MLB", "NHL"] },
  { "id": "creative-013", "text": "Athletes You'd Trust to Hit a Game-Winner With Your Life on the Line", "type": "creative", "leagues": ["NBA", "NFL", "MLB", "NHL"] },
  { "id": "creative-014", "text": "Best Dressed Athletes of All Time", "type": "creative", "leagues": ["NBA", "NFL", "MLB", "NHL"] },
  { "id": "creative-015", "text": "Players Who Made You Fall in Love With Sports", "type": "creative", "leagues": ["NBA", "NFL", "MLB", "NHL"] },
  { "id": "creative-016", "text": "Athletes Who Would Win a Fight Tournament", "type": "creative", "leagues": ["NBA", "NFL", "MLB", "NHL"] },
  { "id": "creative-017", "text": "Most Disrespected Players in History", "type": "creative", "leagues": ["NBA", "NFL", "MLB", "NHL"] },
  { "id": "creative-018", "text": "Players With the Best Pre-Game Routines", "type": "creative", "leagues": ["NBA", "NFL", "MLB", "NHL"] },
  { "id": "creative-019", "text": "Athletes You'd Want Coaching Your Kid's Team", "type": "creative", "leagues": ["NBA", "NFL", "MLB", "NHL"] },
  { "id": "creative-020", "text": "Players Who Were Too Ahead of Their Time", "type": "creative", "leagues": ["NBA", "NFL", "MLB", "NHL"] },
  { "id": "creative-021", "text": "Best Villains in Sports History", "type": "creative", "leagues": ["NBA", "NFL", "MLB", "NHL"] },
  { "id": "creative-022", "text": "Athletes With the Most Iconic Moments", "type": "creative", "leagues": ["NBA", "NFL", "MLB", "NHL"] },
  { "id": "creative-023", "text": "Players Who Peaked at the Perfect Time", "type": "creative", "leagues": ["NBA", "NFL", "MLB", "NHL"] },
  { "id": "creative-024", "text": "Athletes You'd Want on Your Trivia Team", "type": "creative", "leagues": ["NBA", "NFL", "MLB", "NHL"] },
  { "id": "creative-025", "text": "Most Loyal Players in Sports History", "type": "creative", "leagues": ["NBA", "NFL", "MLB", "NHL"] },
  { "id": "creative-026", "text": "Players Who Had the Best Revenge Games", "type": "creative", "leagues": ["NBA", "NFL", "MLB", "NHL"] },
  { "id": "creative-027", "text": "Athletes Who Should Have Their Own Reality Show", "type": "creative", "leagues": ["NBA", "NFL", "MLB", "NHL"] },
  { "id": "creative-028", "text": "Players Who Made the Worst Decisions", "type": "creative", "leagues": ["NBA", "NFL", "MLB", "NHL"] },
  { "id": "creative-029", "text": "Athletes With the Most Swag", "type": "creative", "leagues": ["NBA", "NFL", "MLB", "NHL"] },
  { "id": "creative-030", "text": "Players You'd Pick First in a Schoolyard Draft", "type": "creative", "leagues": ["NBA", "NFL", "MLB", "NHL"] },
  { "id": "creative-031", "text": "Athletes Who'd Win a Cooking Competition", "type": "creative", "leagues": ["NBA", "NFL", "MLB", "NHL"] },
  { "id": "creative-032", "text": "Most Clutch Performers When It Matters Most", "type": "creative", "leagues": ["NBA", "NFL", "MLB", "NHL"] },
  { "id": "creative-033", "text": "Players Your Mom Would Recognize", "type": "creative", "leagues": ["NBA", "NFL", "MLB", "NHL"] },
  { "id": "creative-034", "text": "Athletes Who Got Robbed of Awards", "type": "creative", "leagues": ["NBA", "NFL", "MLB", "NHL"] },
  { "id": "creative-035", "text": "Best Post-Retirement Careers by Athletes", "type": "creative", "leagues": ["NBA", "NFL", "MLB", "NHL"] },
  { "id": "creative-036", "text": "Players Who Had the Best Rookie Moments", "type": "creative", "leagues": ["NBA", "NFL", "MLB", "NHL"] },
  { "id": "creative-037", "text": "Athletes Who'd Be the Best Action Movie Stars", "type": "creative", "leagues": ["NBA", "NFL", "MLB", "NHL"] },
  { "id": "creative-038", "text": "Most Overrated Players of All Time", "type": "creative", "leagues": ["NBA", "NFL", "MLB", "NHL"] },
  { "id": "creative-039", "text": "Players With the Best Signature Moves", "type": "creative", "leagues": ["NBA", "NFL", "MLB", "NHL"] },
  { "id": "creative-040", "text": "Athletes You'd Want Narrating Your Life", "type": "creative", "leagues": ["NBA", "NFL", "MLB", "NHL"] },
  { "id": "creative-041", "text": "Players Who Were the Best Teammates", "type": "creative", "leagues": ["NBA", "NFL", "MLB", "NHL"] },
  { "id": "creative-042", "text": "Athletes With the Craziest What-If Careers", "type": "creative", "leagues": ["NBA", "NFL", "MLB", "NHL"] },

  { "id": "cross-001", "text": "Greatest Number 23s Across All Sports", "type": "cross-league", "leagues": ["NBA", "NFL", "MLB", "NHL"] },
  { "id": "cross-002", "text": "Best Athletes From Texas", "type": "cross-league", "leagues": ["NBA", "NFL", "MLB", "NHL"] },
  { "id": "cross-003", "text": "Most Clutch Performers Across All Sports", "type": "cross-league", "leagues": ["NBA", "NFL", "MLB", "NHL"] },
  { "id": "cross-004", "text": "Greatest Athletes From California", "type": "cross-league", "leagues": ["NBA", "NFL", "MLB", "NHL"] },
  { "id": "cross-005", "text": "Best Athletes Who Played Multiple Sports", "type": "cross-league", "leagues": ["NBA", "NFL", "MLB", "NHL"] },
  { "id": "cross-006", "text": "Most Dominant Athletes of the Last 25 Years", "type": "cross-league", "leagues": ["NBA", "NFL", "MLB", "NHL"] },
  { "id": "cross-007", "text": "Greatest International Athletes in American Sports", "type": "cross-league", "leagues": ["NBA", "NFL", "MLB", "NHL"] },
  { "id": "cross-008", "text": "Best Athletes From New York", "type": "cross-league", "leagues": ["NBA", "NFL", "MLB", "NHL"] },
  { "id": "cross-009", "text": "Most Marketable Athletes of All Time", "type": "cross-league", "leagues": ["NBA", "NFL", "MLB", "NHL"] },
  { "id": "cross-010", "text": "Greatest Left-Handed Athletes", "type": "cross-league", "leagues": ["NBA", "NFL", "MLB", "NHL"] },
  { "id": "cross-011", "text": "Best Athletes From Florida", "type": "cross-league", "leagues": ["NBA", "NFL", "MLB", "NHL"] },
  { "id": "cross-012", "text": "Most Feared Competitors Across All Sports", "type": "cross-league", "leagues": ["NBA", "NFL", "MLB", "NHL"] },
  { "id": "cross-013", "text": "Greatest Athletes Who Wore Number 12", "type": "cross-league", "leagues": ["NBA", "NFL", "MLB", "NHL"] },
  { "id": "cross-014", "text": "Best Father-Son Duos in Sports", "type": "cross-league", "leagues": ["NBA", "NFL", "MLB", "NHL"] },
  { "id": "cross-015", "text": "Most Iconic Jersey Numbers Across All Sports", "type": "cross-league", "leagues": ["NBA", "NFL", "MLB", "NHL"] },
  { "id": "cross-016", "text": "Greatest Athletes From Ohio", "type": "cross-league", "leagues": ["NBA", "NFL", "MLB", "NHL"] },
  { "id": "cross-017", "text": "Best Athlete Comebacks From Injury", "type": "cross-league", "leagues": ["NBA", "NFL", "MLB", "NHL"] },
  { "id": "cross-018", "text": "Most Dominant Playoff Performers Across Sports", "type": "cross-league", "leagues": ["NBA", "NFL", "MLB", "NHL"] },
  { "id": "cross-019", "text": "Greatest Athletes From the SEC", "type": "cross-league", "leagues": ["NBA", "NFL", "MLB"] },
  { "id": "cross-020", "text": "Best Athletes Who Went to the Same College", "type": "cross-league", "leagues": ["NBA", "NFL", "MLB", "NHL"] },
  { "id": "cross-021", "text": "Most Inspiring Athletes of All Time", "type": "cross-league", "leagues": ["NBA", "NFL", "MLB", "NHL"] },
  { "id": "cross-022", "text": "Greatest Athletes From Chicago", "type": "cross-league", "leagues": ["NBA", "NFL", "MLB", "NHL"] },
  { "id": "cross-023", "text": "Best Athletes Under 6 Feet Tall", "type": "cross-league", "leagues": ["NBA", "NFL", "MLB", "NHL"] },
  { "id": "cross-024", "text": "Most Dominant Athletes in Their Physical Prime", "type": "cross-league", "leagues": ["NBA", "NFL", "MLB", "NHL"] },
  { "id": "cross-025", "text": "Greatest Brother Duos in Sports History", "type": "cross-league", "leagues": ["NBA", "NFL", "MLB", "NHL"] }
]
